lasutils/__init__.py
lasutils/api_poller.py
lasutils/connector.py
lasutils/deserializer.py
lasutils/exceptions.py
lasutils/helpers.py
lasutils/keyvault.py
lasutils/las_api.py
lasutils/my_ffmpeg.py
lasutils/serializer.py
lasutils/settings.py
lasutils/variable_parser.py
lasutils-1.0.85.dist-info/METADATA
lasutils-1.0.85.dist-info/WHEEL
lasutils-1.0.85.dist-info/RECORD
