Metadata-Version: 2.4
Name: lasutils
Version: 1.0.85
Summary: LAS utils
Project-URL: Homepage, https://livearenasports.com/
Author-email: Johan Gustavsson <johan.gustavsson@sportway.com>
Classifier: License :: OSI Approved :: MIT License
Classifier: Operating System :: OS Independent
Classifier: Programming Language :: Python :: 3
Requires-Python: >=3.10
Requires-Dist: azure-identity
Requires-Dist: azure-keyvault
Requires-Dist: python-dateutil
Requires-Dist: python-dotenv
Requires-Dist: pytz
Requires-Dist: pyyaml
Requires-Dist: requests
Requires-Dist: typer
Requires-Dist: xmltodict
